setup.py
distributions_sb/Binomialdistribution.py
distributions_sb/Gaussiandistribution.py
distributions_sb/Generaldistribution.py
distributions_sb/__init__.py
distributions_sb.egg-info/PKG-INFO
distributions_sb.egg-info/SOURCES.txt
distributions_sb.egg-info/dependency_links.txt
distributions_sb.egg-info/not-zip-safe
distributions_sb.egg-info/top_level.txt