Metadata-Version: 1.0
Name: distributions-sb
Version: 0.1
Summary: Gaussian distributions
Home-page: UNKNOWN
Author: Shubham Barthwal
Author-email: shubhambarthwal94@gmail.com
License: UNKNOWN
Platform: UNKNOWN
